rust_pyspec_glue-0.0.9.dist-info/METADATA
rust_pyspec_glue-0.0.9.dist-info/WHEEL
rust_pyspec_glue-0.0.9.dist-info/licenses/LICENSE
rust_pyspec_glue/py.typed
rust_pyspec_glue/__init__.py
rust_pyspec_glue/rust_pyspec_glue/__init__.py
rust_pyspec_glue/rust_pyspec_glue/ffi.py
rust_pyspec_glue/rust_pyspec_glue/rust_pyspec_glue.so
rust_pyspec_glue-0.0.9.dist-info/RECORD
