Metadata-Version: 2.3
Name: rust-pyspec-glue
Version: 0.0.9
Classifier: Programming Language :: Rust
Classifier: Programming Language :: Python :: Implementation :: CPython
Classifier: Programming Language :: Python :: Implementation :: PyPy
Requires-Dist: cffi
License-File: LICENSE
Requires-Python: >=3.6
